Metadata-Version: 1.0
Name: nr-Aws-ml1
Version: 0.1
Summary: Gaussian and binomial distributions
Home-page: UNKNOWN
Author: Nusrat Rani
Author-email: UNKNOWN
License: UNKNOWN
Platform: UNKNOWN
